Metadata-Version: 2.1
Name: cz-data-diff
Version: 0.0.4
Summary: Command-line tool and Python library to efficiently diff rows across two different databases.
Home-page: https://github.com/datafold/data-diff
License: MIT
Author: Datafold
Author-email: data-diff@datafold.com
Requires-Python: >=3.8.0,<4.0.0
Classifier: Development Status :: 2 - Pre-Alpha
Classifier: Environment :: Console
Classifier: Intended Audience :: Developers
Classifier: Intended Audience :: Information Technology
Classifier: Intended Audience :: System Administrators
Classifier: License :: OSI Approved :: MIT License
Classifier: Programming Language :: Python :: 3
Classifier: Programming Language :: Python :: 3.8
Classifier: Programming Language :: Python :: 3.9
Classifier: Programming Language :: Python :: 3.10
Classifier: Programming Language :: Python :: 3.11
Classifier: Programming Language :: Python :: 3.12
Classifier: Topic :: Database :: Database Engines/Servers
Classifier: Typing :: Typed
Provides-Extra: clickhouse
Provides-Extra: clickzetta
Provides-Extra: duckdb
Provides-Extra: mssql
Provides-Extra: mysql
Provides-Extra: oracle
Provides-Extra: postgresql
Provides-Extra: preql
Provides-Extra: presto
Provides-Extra: redshift
Provides-Extra: snowflake
Provides-Extra: trino
Provides-Extra: vertica
Requires-Dist: attrs (>=23.1.0,<24.0.0)
Requires-Dist: click (>=8.1,<9.0)
Requires-Dist: clickhouse-driver ; extra == "clickhouse"
Requires-Dist: clickzetta-connector (>=0.8.51) ; extra == "clickzetta"
Requires-Dist: cryptography ; extra == "snowflake"
Requires-Dist: dbt-core (>=1.0.0,<2.0.0)
Requires-Dist: dsnparse (<0.2.0)
Requires-Dist: duckdb ; extra == "duckdb"
Requires-Dist: keyring
Requires-Dist: mashumaro[msgpack] (>=3.8.1,<3.9.0)
Requires-Dist: mysql-connector-python (==8.0.29) ; extra == "mysql"
Requires-Dist: oracledb ; extra == "oracle"
Requires-Dist: preql (>=0.2.19,<0.3.0) ; extra == "preql"
Requires-Dist: presto-python-client ; extra == "presto"
Requires-Dist: psycopg2 ; extra == "postgresql" or extra == "redshift"
Requires-Dist: pydantic (==1.10.12)
Requires-Dist: pyodbc (>=4.0.39,<5.0.0) ; extra == "mssql"
Requires-Dist: rich
Requires-Dist: snowflake-connector-python (>=3.0.2,<4.0.0) ; extra == "snowflake"
Requires-Dist: tabulate (>=0.9.0,<0.10.0)
Requires-Dist: toml (>=0.10.2,<0.11.0)
Requires-Dist: trino (>=0.314.0,<0.315.0) ; extra == "trino"
Requires-Dist: typing-extensions (>=4.0.1)
Requires-Dist: urllib3 (<2)
Requires-Dist: vertica-python ; extra == "vertica"
Project-URL: Documentation, https://docs.datafold.com/reference/open_source/cli
Project-URL: Repository, https://github.com/datafold/data-diff
